fluxvis/__init__.py
fluxvis/__main__.py
fluxvis/__version__.py
fluxvis/a2rchery.py
fluxvis/invpolar.py
fluxvis/notebook.py
fluxvis/greaseweazle/__init__.py
fluxvis/greaseweazle/error.py
fluxvis/greaseweazle/flux.py
fluxvis/greaseweazle/track.py
fluxvis/greaseweazle/codec/__init__.py
fluxvis/greaseweazle/codec/formats.py
fluxvis/greaseweazle/image/__init__.py
fluxvis/greaseweazle/image/acorn.py
fluxvis/greaseweazle/image/adf.py
fluxvis/greaseweazle/image/d81.py
fluxvis/greaseweazle/image/edsk.py
fluxvis/greaseweazle/image/hfe.py
fluxvis/greaseweazle/image/image.py
fluxvis/greaseweazle/image/img.py
fluxvis/greaseweazle/image/ipf.py
fluxvis/greaseweazle/image/kryoflux.py
fluxvis/greaseweazle/image/scp.py
fluxvis/greaseweazle/image/sf7.py
fluxvis/greaseweazle/tools/__init__.py
fluxvis/greaseweazle/tools/util.py
fluxvis-1.0.0a5.dist-info/METADATA
fluxvis-1.0.0a5.dist-info/WHEEL
fluxvis-1.0.0a5.dist-info/entry_points.txt
fluxvis-1.0.0a5.dist-info/top_level.txt
fluxvis-1.0.0a5.dist-info/RECORD
