Metadata-Version: 2.2
Name: fluxvis
Version: 1.0.0a5
Home-page: https://github.com/adafruit/fluxvis
Author: Jeff Epler for Adafruit Industries
Author-email: jeff@adafruit.com
Classifier: Programming Language :: Python :: 3
Requires-Python: >=3.9
Requires-Dist: click
Requires-Dist: numpy
Requires-Dist: matplotlib
Requires-Dist: scikit_image
